contractKit/__init__.py
contractKit/extractor.py
contractKit/parser.py
contractKit/pdf_reader.py
contractKit/summarizer.py
contractkit-0.1.1.dist-info/METADATA
contractkit-0.1.1.dist-info/WHEEL
contractkit-0.1.1.dist-info/top_level.txt
contractkit-0.1.1.dist-info/RECORD
