Metadata-Version: 2.4
Name: contractkit
Version: 0.1.1
Summary: A Python library for contract analysis using LLMs
Home-page: https://github.com/Eskaykaushik/contractKit.git
Author: Shubham Kaushik
Author-email: eskaykaushik2@gmail.com
Classifier: Programming Language :: Python :: 3
Classifier: Operating System :: OS Independent
Requires-Python: >=3.7
Requires-Dist: openai
Requires-Dist: PyPDF2
Requires-Dist: python-dotenv
Dynamic: author
Dynamic: author-email
Dynamic: classifier
Dynamic: description
Dynamic: description-content-type
Dynamic: home-page
Dynamic: requires-dist
Dynamic: requires-python
Dynamic: summary
